pyxtrabackup-3.1.4.dist-info/DESCRIPTION.rst
pyxtrabackup-3.1.4.dist-info/METADATA
pyxtrabackup-3.1.4.dist-info/RECORD
pyxtrabackup-3.1.4.dist-info/WHEEL
pyxtrabackup-3.1.4.dist-info/entry_points.txt
pyxtrabackup-3.1.4.dist-info/metadata.json
pyxtrabackup-3.1.4.dist-info/pbr.json
pyxtrabackup-3.1.4.dist-info/top_level.txt
xtrabackup/__about__.py
xtrabackup/__init__.py
xtrabackup/backup_tools.py
xtrabackup/command_executor.py
xtrabackup/exception.py
xtrabackup/filesystem_utils.py
xtrabackup/full_backup.py
xtrabackup/http_manager.py
xtrabackup/incremental_backup.py
xtrabackup/log_manager.py
xtrabackup/restoration.py
xtrabackup/restoration_tools.py
xtrabackup/timer.py
