Metadata-Version: 2.0
Name: pyxtrabackup
Version: 3.1.4
Summary: Percona Xtrabackup python wrapper
Home-page: https://github.com/deviantony/xtrabackup-scripts
Author: Anthony Lapenna
Author-email: lapenna.anthony@gmail.com
License: Apache License, Version 2.0
Keywords: mysql mariadb database backup percona xtrabackup
Platform: UNKNOWN
Classifier: Intended Audience :: System Administrators
Classifier: Topic :: System :: Archiving :: Backup
Classifier: License :: OSI Approved :: Apache Software License
Classifier: Programming Language :: Python :: 2
Classifier: Programming Language :: Python :: 2.7
Classifier: Programming Language :: Python :: 3
Classifier: Programming Language :: Python :: 3.4
Requires-Dist: docopt
Requires-Dist: requests
